lorien_demo/__init__.py
lorien_demo/cli.py
lorien_demo-0.1.0.dist-info/METADATA
lorien_demo-0.1.0.dist-info/WHEEL
lorien_demo-0.1.0.dist-info/entry_points.txt
lorien_demo-0.1.0.dist-info/top_level.txt
lorien_demo-0.1.0.dist-info/RECORD
