Metadata-Version: 2.4
Name: lorien-demo
Version: 0.1.0
Summary: Lorien 项目初始化工具
Author-email: lorien <1173381395@qq.com>
License: MIT License
Classifier: Programming Language :: Python :: 3
Classifier: License :: OSI Approved :: MIT License
Classifier: Operating System :: OS Independent
Requires-Python: >=3.7
